wplace/__init__.py
wplace/api.py
wplace/canvas.py
wplace/color.py
wplace/country.py
wplace/dto.py
wplace/temp.py
wplace/utils.py
wplace-0.0.5.dist-info/METADATA
wplace-0.0.5.dist-info/WHEEL
wplace-0.0.5.dist-info/top_level.txt
wplace-0.0.5.dist-info/RECORD
