Metadata-Version: 2.4
Name: wplace
Version: 0.0.5
Summary: Utility classes and methods for Wplace.live
Author-email: Boscawinks <bosca.winks@gmx.de>
Project-URL: Homepage, https://github.com/boscawinks/wplace
Project-URL: Repository, https://github.com/boscawinks/wplace
Project-URL: Issues, https://github.com/boscawinks/wplace/issues
Classifier: Development Status :: 2 - Pre-Alpha
Classifier: Programming Language :: Python :: 3
Classifier: Operating System :: OS Independent
Classifier: Topic :: Utilities
Requires-Python: >=3.10.12
Requires-Dist: cloudscraper>=1.2.71
Requires-Dist: pillow>=11.3.0
Requires-Dist: pyproj>=3.7.1
Requires-Dist: rasterio>=1.4.3
